lilcache/__init__.py
lilcache/cache.py
lilcache/util.py
lilcache-0.0.1.dist-info/LICENSE
lilcache-0.0.1.dist-info/METADATA
lilcache-0.0.1.dist-info/WHEEL
lilcache-0.0.1.dist-info/top_level.txt
lilcache-0.0.1.dist-info/RECORD
