Metadata-Version: 2.1
Name: lilcache
Version: 0.0.1
Summary: Inter process and thread safe light weight cache
Home-page: https://github.com/return007/lilcache
Author: return007
Author-email: glalchandanig@gmail.com
License: UNKNOWN
Platform: UNKNOWN
Classifier: License :: OSI Approved :: MIT License
Classifier: Development Status :: 2 - Pre-Alpha
Requires-Python: >=2.7
Provides-Extra: dev
Requires-Dist: pytest ; extra == 'dev'
Requires-Dist: sphinx ; extra == 'dev'
